<?xml version="1.0" encoding="UTF-8" ?>
<!DOCTYPE mapper PUBLIC "-//mybatis.org//DTD Mapper 3.0//EN" "http://mybatis.org/dtd/mybatis-3-mapper.dtd" >
<mapper namespace="org.tetram.bdtheque.data.dao.mappers.EditionMapper">
    <resultMap id="EditionLite" type="beanEditionLite">
        <id column="id_edition" property="id"/>
        <result column="anneeedition" property="anneeEdition"/>
        <result column="isbn" property="isbn"/>
        <association property="editeur" select="org.tetram.bdtheque.data.dao.mappers.EditeurMapper.getEditeurLiteById"
                     column="id_editeur"/>
        <association property="collection"
                     select="org.tetram.bdtheque.data.dao.mappers.CollectionMapper.getCollectionLiteById"
                     column="id_collection"/>
    </resultMap>
    <resultMap id="EditionFull" type="beanEdition">
        <id column="id_edition" property="id"/>
        <!-- voir pour remplacer par un albumlite -->
        <result column="id_album" property="idAlbum"/>
        <result column="anneeEdition" property="anneeEdition"/>
        <result column="prix" property="prix"/>
        <result column="vo" property="vo"/>
        <result column="couleur" property="couleur"/>
        <result column="dedicace" property="dedicace"/>
        <result column="offert" property="offert"/>
        <result column="gratuit" property="gratuit"/>
        <result column="stock" property="stock"/>
        <result column="prete" property="prete"/>
        <result column="isbn" property="isbn"/>
        <result column="typeEdition" property="typeEdition"/>
        <result column="etat" property="etat"/>
        <result column="reliure" property="reliure"/>
        <result column="orientation" property="orientation"/>
        <result column="formatEdition" property="formatEdition"/>
        <result column="sensLecture" property="sensLecture"/>
        <result column="nombreDePages" property="nombreDePages"/>
        <result column="dateAchat" property="dateAchat"/>
        <result column="notes" property="notes"/>
        <result column="anneeCote" property="anneeCote"/>
        <result column="prixCote" property="prixCote"/>
        <result column="numeroPerso" property="numeroPerso"/>
        <association property="editeur" select="org.tetram.bdtheque.data.dao.mappers.EditeurMapper.getEditeurById"
                     column="id_editeur"/>
        <association property="collection"
                     select="org.tetram.bdtheque.data.dao.mappers.CollectionMapper.getCollectionById"
                     column="id_collection"/>
        <collection property="couvertures"
                    select="org.tetram.bdtheque.data.dao.mappers.ImageMapper.getListCouvertureLiteByEditionId"
                    column="id_edition"/>
    </resultMap>

    <select id="getEditionLiteById" resultMap="EditionLite">
        <![CDATA[
        select
            id_edition, anneeEdition, isbn, id_editeur, id_collection
        from
            editions
        where
            id_edition = #{id}
        ]]>
    </select>

    <sql id="selectEditionFull">
        <![CDATA[
        select
            e.id_edition, e.id_album, e.id_editeur, e.id_collection, e.anneeEdition, e.prix, e.vo,
            e.couleur, e.isbn, e.dedicace, e.prete, e.stock, e.offert, e.gratuit, e.nombreDePages, e.dateAchat, e.notes,
            e.anneeCote, e.prixCote, e.numeroPerso,
            e.etat, le.libelle as lb_etat,
            e.reliure, lr.libelle as lb_reliure,
            e.orientation, lo.libelle as lb_orientation,
            e.formatEdition, lf.libelle as lb_formatEdition,
            e.typeEdition, lte.libelle as lb_typeEdition,
            e.sensLecture, lsl.libelle as lb_sensLecture
        from
            editions e
            left join listes le on
                (le.ref = e.etat and le.categorie = 1)
            left join listes lr on
                (lr.ref = e.reliure and lr.categorie = 2)
            left join listes lte on
                (lte.ref = e.typeEdition and lte.categorie = 3)
            left join listes lo on
                (lo.ref = e.orientation and lo.categorie = 4)
            left join listes lf on
                (lf.ref = e.formatEdition and lf.categorie = 5)
            left join listes lsl on
                (lsl.ref = e.sensLecture and lsl.categorie = 8)
        ]]>
    </sql>

    <select id="getEditionById" parameterType="UUID" resultMap="EditionFull">
        <include refid="selectEditionFull"/>
        <where>
            e.id_edition = #{id}
        </where>
    </select>
    <select id="getListEditionByAlbumId" resultMap="EditionFull">
        <include refid="selectEditionFull"/>
        <where>
            e.id_album = #{id}
            <if test="stock != null">
                and e.stock = #{stock}
            </if>
        </where>
    </select>

    <delete id="cleanEditionsAlbum">
        <![CDATA[
        delete from editions
        where
            id_album = #{idAlbum}
        ]]>
        <if test="editions != null and !editions.isEmpty">
            and id_edition not in
            <foreach collection="editions" item="item" index="index" open="(" separator="," close=")">
                #{item.id}
            </foreach>
        </if>
    </delete>

    <sql id="saveEdition">
        <![CDATA[
        update or insert into editions (
            id_edition, id_album, id_editeur, id_collection, anneeEdition, prix, vo, typeEdition,
            couleur, isbn, stock, dedicace, offert, gratuit, etat, reliure, orientation, formatEdition,
            dateAchat, notes, nombreDePages, anneeCote, prixCote, numeroPerso, sensLecture
        ) values (
            #{id}, #{idAlbum}, #{idEditeur}, #{idCollection}, #{anneeEdition}, #{prix}, #{vo}, #{typeEdition},
            #{couleur}, #{isbn}, #{stock}, #{dedicace}, #{offert}, #{gratuit}, #{etat}, #{reliure}, #{orientation}, #{formatEdition},
            #{dateAchat}, #{notes}, #{nombreDePages}, #{anneeCote}, #{prixCote}, #{numeroPerso}, #{sensLecture}
        )
        ]]>
    </sql>

    <insert id="createEdition">
        <selectKey keyProperty="id" order="BEFORE" resultType="UUID">
            <include refid="org.tetram.bdtheque.data.dao.mappers.CommonMapper.autoIncKey"/>
        </selectKey>
        <include refid="saveEdition"/>
    </insert>

    <update id="updateEdition">
        <include refid="saveEdition"/>
    </update>

    <delete id="deleteEdition">
        <![CDATA[
        delete from editions where id_edition = #{id}
        ]]>
    </delete>

</mapper>